metamatrix/__init__.py
metamatrix/core.py
metamatrix-0.1.0.dist-info/METADATA
metamatrix-0.1.0.dist-info/WHEEL
metamatrix-0.1.0.dist-info/top_level.txt
metamatrix-0.1.0.dist-info/RECORD
