Metadata-Version: 2.4
Name: metamatrix
Version: 0.1.0
Summary: Add your description here
Requires-Python: >=3.13
Requires-Dist: marimo>=0.14.10
Requires-Dist: matplotlib>=3.10.3
Requires-Dist: numpy>=2.3.1
Requires-Dist: pandas>=2.3.1
Requires-Dist: svg-py>=1.7.0
